OSSS/__init__.py
OSSS/__main__.py
OSSS/cli.py
OSSS/main.py
OSSS/resources.py
OSSS/settings.py
OSSS/api/__init__.py
OSSS/api/auth_proxy.py
OSSS/api/debug.py
OSSS/api/router_factory.py
OSSS/api/generated_resources/__init__.py
OSSS/api/generated_resources/factory.py
OSSS/api/generated_resources/register_all.py
OSSS/api/generated_resources/serialization.py
OSSS/api/routers/__init__.py
OSSS/api/routers/auth_flow.py
OSSS/api/routers/health.py
OSSS/api/routers/me.py
OSSS/auth/__init__.py
OSSS/auth/dependencies.py
OSSS/auth/deps.py
OSSS/auth/deps_fresh.py
OSSS/auth/introspection.py
OSSS/auth/jwt.py
OSSS/auth/keycloak.py
OSSS/auth/roles.py
OSSS/core/config.py
OSSS/db/__init__.py
OSSS/db/base.py
OSSS/db/session.py
OSSS/db/migrations/env.py
OSSS/db/migrations/versions/0001_init.py
OSSS/db/migrations/versions/0002_add_tables.py
OSSS/db/migrations/versions/0003_populate_states_table.py
OSSS/db/migrations/versions/0004_populate_organizations_table.py
OSSS/db/migrations/versions/0005_populate_schools_table.py
OSSS/db/migrations/versions/0006_populate_behavior_codes.py
OSSS/db/migrations/versions/0007_populate_academic_terms.py
OSSS/db/migrations/versions/0008_populate_standardized_tests.py
OSSS/db/migrations/versions/0009_populate_attendance_codes.py
OSSS/db/migrations/versions/0010_populate_roles.py
OSSS/db/migrations/versions/0011_populate_permissions.py
OSSS/db/migrations/versions/0012_populate_departments.py
OSSS/db/migrations/versions/0013_populate_subjects.py
OSSS/db/migrations/versions/0014_populate_courses.py
OSSS/db/migrations/versions/0015_populate_grading_periods.py
OSSS/db/migrations/versions/0016_populate_bus_routes.py
OSSS/db/migrations/versions/0017_populate_students.py
OSSS/db/migrations/versions/0018_populate_positions.py
OSSS/db/migrations/versions/0019_seed_remaining_tables.py
OSSS/db/models/__init__.py
OSSS/db/models/_helpers.py
OSSS/db/models/academic_terms.py
OSSS/db/models/accommodations.py
OSSS/db/models/activities.py
OSSS/db/models/addresses.py
open_schools-0.0.0.dev2.dist-info/licenses/LICENSE
open_schools-0.0.0.dev2.dist-info/METADATA
open_schools-0.0.0.dev2.dist-info/WHEEL
open_schools-0.0.0.dev2.dist-info/entry_points.txt
open_schools-0.0.0.dev2.dist-info/top_level.txt
open_schools-0.0.0.dev2.dist-info/RECORD
