Metadata-Version: 2.4
Name: open-schools
Version: 0.0.0.dev2
Summary: Open Source School Software(OSSS)
Author-email: Will Rubel <will.rubel@gmail.com>
Maintainer-email: Will Rubel <will.rubel@gmail.com>
License: Apache-2.0
Project-URL: documentation, https://osss.com/
Project-URL: repository, https://github.com/rubelw/OSSS
Project-URL: issues, https://github.com/rubelw/OSSS/issues
Keywords: Keycloak,FastAPI,Authentication,Authorization,School
Classifier: Development Status :: 3 - Alpha
Classifier: Intended Audience :: Developers
Classifier: Topic :: Internet :: WWW/HTTP :: Session
Classifier: Topic :: Internet :: WWW/HTTP :: WSGI
Classifier: Topic :: Software Development :: Libraries :: Application Frameworks
Classifier: Topic :: Software Development :: Libraries :: Python Modules
Classifier: Framework :: FastAPI
Classifier: License :: OSI Approved :: Apache Software License
Classifier: Programming Language :: Python :: 3.9
Classifier: Programming Language :: Python :: 3.10
Classifier: Programming Language :: Python :: 3.11
Classifier: Programming Language :: Python :: 3.12
Requires-Python: >=3.11
License-File: LICENSE
Requires-Dist: anyio>=3.4.0
Requires-Dist: asgiref>=3.4.1
Requires-Dist: certifi>=2023.7.22
Requires-Dist: charset-normalizer>=2.0.9
Requires-Dist: click>=8.0.3
Requires-Dist: ecdsa>=0.17.0
Requires-Dist: fastapi>=0.110.0
Requires-Dist: pydantic>=2.6
Requires-Dist: uvicorn>=0.22
Requires-Dist: h11>=0.12.0
Requires-Dist: idna>=3.3
Requires-Dist: pyasn1>=0.4.8
Requires-Dist: python-jose[cryptography]>=3.3.0
Requires-Dist: requests>=2.31.0
Requires-Dist: rsa>=4.8
Requires-Dist: six>=1.16.0
Requires-Dist: sniffio>=1.2.0
Requires-Dist: typing_extensions>=4.0.1
Requires-Dist: urllib3>=1.26.17
Requires-Dist: itsdangerous>=2.0.1
Requires-Dist: cryptography>=41.0.0
Requires-Dist: alembic>=1.13.0
Requires-Dist: sqlalchemy>=2.0.0
Requires-Dist: psycopg2-binary>=2.9.9
Requires-Dist: fastapi-cache2>=0.2.1
Requires-Dist: redis>=5.0.0
Requires-Dist: httpx>=0.24
Requires-Dist: httpretty>=1.1.4
Requires-Dist: python-multipart>=0.0.9
Requires-Dist: jwt>=1.4.0
Requires-Dist: PyJWT>=2.10.1
Requires-Dist: pydantic-settings>=2.10.1
Requires-Dist: python-dotenv>=1.1.1
Requires-Dist: asyncpg>=0.30.0
Requires-Dist: typer[all]>=0.12
Requires-Dist: httpx>=0.27
Requires-Dist: rich>=13.7
Requires-Dist: tomli-w>=1.0
Requires-Dist: tomli>=2.0; python_version < "3.11"
Requires-Dist: fastapi
Requires-Dist: uvicorn
Requires-Dist: httpx>=0.24
Requires-Dist: python-jose[cryptography]>=3.3
Requires-Dist: click
Requires-Dist: httpx
Requires-Dist: rich
Requires-Dist: tomli_w
Provides-Extra: server
Requires-Dist: gunicorn>=21.2; extra == "server"
Provides-Extra: dev
Requires-Dist: pytest>=8.3.4; extra == "dev"
Requires-Dist: pytest-cov>=6.0.0; extra == "dev"
Requires-Dist: mkdocs>=1.6.0; extra == "dev"
Requires-Dist: mkdocs-material>=9.5.0; extra == "dev"
Requires-Dist: mkdocstrings[python]>=0.26.0; extra == "dev"
Requires-Dist: markdown-include>=0.8.1; extra == "dev"
Dynamic: license-file
